LICENSE.txt
README.md
setup.py
bin/nuri
bin/sampling.py
bin/vmr_wavelet.py
bin/wavevid.py
nuri/__init__.py
nuri/utils.py
nuri.egg-info/PKG-INFO
nuri.egg-info/SOURCES.txt
nuri.egg-info/dependency_links.txt
nuri.egg-info/requires.txt
nuri.egg-info/top_level.txt
nuri/analysis/__init__.py
nuri/analysis/fitting.py
nuri/analysis/normalize.py
nuri/analysis/plots.py
nuri/extract/__init__.py
nuri/extract/check24hrs.py
nuri/extract/extract.py
nuri/extract/server.py
nuri/extract/split.py
nuri/projects/__init__.py
nuri/projects/fftcomp.py
nuri/projects/timing.py
nuri/projects/timing2.py
nuri/projects/transform.py