Metadata-Version: 2.1
Name: nuri
Version: 1.0.0
Summary: Time-frequency and sensor network analysis software for urban magnetometry data.
Home-page: http://citymag.gitlab.io/nuri/
Author: Vincent Dumont
Author-email: vincentdumont11@gmail.com
Maintainer: Vincent Dumont
Maintainer-email: vincentdumont11@gmail.com
License: UNKNOWN
Project-URL: Source Code, https://gitlab.com/citymag/analysis/nuri
Platform: UNKNOWN
Classifier: Intended Audience :: Science/Research
Classifier: License :: Other/Proprietary License
Classifier: Natural Language :: English
Classifier: Operating System :: OS Independent
Classifier: Programming Language :: Python
Classifier: Topic :: Scientific/Engineering :: Physics
License-File: LICENSE.txt
